{"name":": Registro en uiTest","id":"prueba-reto-sophos;:-registro-en-uitest","testSteps":[{"number":1,"description":"Example: {firstname\u003djhon, lastname\u003dsmith, email\u003djhon@gmail.com, month\u003dMarch, day\u003d3, year\u003d1980, city\u003dMedellín, Antioquía, Colombia, postalcod\u003d050010}","duration":28194,"startTime":"2020-12-19T21:14:03.054-05:00[America/Bogota]","screenshots":[{"screenshot":"5d89f945cdfec69d6621cab59df70f3ef2a092400e2752ba48239b5d3a5bce22.png","timeStamp":1608430471248}],"result":"SUCCESS","precondition":false,"level":0,"children":[{"number":2,"description":"Dado abro la pagina","duration":15162,"startTime":"2020-12-19T21:14:03.110-05:00[America/Bogota]","screenshots":[{"screenshot":"5ce352830e8b9d6e3e9847f27a0f68be3ee1a5cb97ef34b2c8463051982e16a8.png","timeStamp":1608430458271}],"result":"SUCCESS","precondition":false,"level":1,"children":[{"number":3,"description":"User abrirpagina","duration":14767,"startTime":"2020-12-19T21:14:03.501-05:00[America/Bogota]","screenshots":[{"screenshot":"5ce352830e8b9d6e3e9847f27a0f68be3ee1a5cb97ef34b2c8463051982e16a8.png","timeStamp":1608430458268}],"result":"SUCCESS","precondition":false,"level":2,"children":[{"number":4,"description":"user opens the https://www.utest.com/","duration":14717,"startTime":"2020-12-19T21:14:03.537-05:00[America/Bogota]","screenshots":[{"screenshot":"5ce352830e8b9d6e3e9847f27a0f68be3ee1a5cb97ef34b2c8463051982e16a8.png","timeStamp":1608430458254}],"result":"SUCCESS","precondition":false,"level":3}]}]},{"number":5,"description":"Cuando me quiero registrar con los datos personales\r\n| firstname | lastname | email | month | day | year |\r\n| jhon | smith | jhon@gmail.com | March | 3 | 1980 |","duration":6981,"startTime":"2020-12-19T21:14:18.273-05:00[America/Bogota]","screenshots":[{"screenshot":"5ce352830e8b9d6e3e9847f27a0f68be3ee1a5cb97ef34b2c8463051982e16a8.png","timeStamp":1608430458275},{"screenshot":"3421a7ac9633f8c07fdd0dc78ff6056a5f66e9f05cd93d03482ed435a597ba88.png","timeStamp":1608430465254}],"result":"SUCCESS","precondition":false,"level":1,"children":[{"number":6,"description":"User utest task","duration":1526,"startTime":"2020-12-19T21:14:18.303-05:00[America/Bogota]","screenshots":[{"screenshot":"2dd23d2542462ffb286b1a3e02a6e01d68118ae9546944481f9ea2b789ff858c.png","timeStamp":1608430458781},{"screenshot":"d27bef1922900fd6496833e61cd5b33fc8024ed37aacbfc0b3d376c996c56a32.png","timeStamp":1608430459829}],"result":"SUCCESS","precondition":false,"level":2,"children":[{"number":7,"description":"user clicks on boton login","duration":1026,"startTime":"2020-12-19T21:14:18.800-05:00[America/Bogota]","screenshots":[{"screenshot":"2dd23d2542462ffb286b1a3e02a6e01d68118ae9546944481f9ea2b789ff858c.png","timeStamp":1608430458805},{"screenshot":"d27bef1922900fd6496833e61cd5b33fc8024ed37aacbfc0b3d376c996c56a32.png","timeStamp":1608430459825}],"result":"SUCCESS","precondition":false,"level":3}]},{"number":8,"description":"User paso datos personales","duration":5420,"startTime":"2020-12-19T21:14:19.831-05:00[America/Bogota]","screenshots":[{"screenshot":"d27bef1922900fd6496833e61cd5b33fc8024ed37aacbfc0b3d376c996c56a32.png","timeStamp":1608430459833},{"screenshot":"3421a7ac9633f8c07fdd0dc78ff6056a5f66e9f05cd93d03482ed435a597ba88.png","timeStamp":1608430465251}],"result":"SUCCESS","precondition":false,"level":2,"children":[{"number":9,"description":"user enters \u0027jhon\u0027 into campo nombre","duration":1353,"startTime":"2020-12-19T21:14:19.908-05:00[America/Bogota]","screenshots":[{"screenshot":"a722d896928b3f7b494de2fbbdc3fb7fa554ea5e5af95514f37898db46de8509.png","timeStamp":1608430460523},{"screenshot":"c29a8f9b1eb27c37190f58c1d10d6557731ac502e7ea867e9debbd1ded35571e.png","timeStamp":1608430461261}],"result":"SUCCESS","precondition":false,"level":3},{"number":10,"description":"user enters \u0027smith\u0027 into campo apellido","duration":658,"startTime":"2020-12-19T21:14:21.263-05:00[America/Bogota]","screenshots":[{"screenshot":"c29a8f9b1eb27c37190f58c1d10d6557731ac502e7ea867e9debbd1ded35571e.png","timeStamp":1608430461264},{"screenshot":"ec89be471a6507c3758118fca4e900f13983ffbbf00812e01c04f6679e11ab98.png","timeStamp":1608430461921}],"result":"SUCCESS","precondition":false,"level":3},{"number":11,"description":"user enters \u0027jhon@gmail.com\u0027 into campo email","duration":692,"startTime":"2020-12-19T21:14:21.923-05:00[America/Bogota]","screenshots":[{"screenshot":"ec89be471a6507c3758118fca4e900f13983ffbbf00812e01c04f6679e11ab98.png","timeStamp":1608430461925},{"screenshot":"ae13a29cebd74258b194298ea22ddcc35eacbfd9258e3c43fa8c73f455a4458a.png","timeStamp":1608430462615}],"result":"SUCCESS","precondition":false,"level":3},{"number":12,"description":"user select March on mes","duration":688,"startTime":"2020-12-19T21:14:22.617-05:00[America/Bogota]","screenshots":[{"screenshot":"ae13a29cebd74258b194298ea22ddcc35eacbfd9258e3c43fa8c73f455a4458a.png","timeStamp":1608430462620},{"screenshot":"792663569b2b5dc21e79487f419835e68fbb3a2c4dcb00f2a54828d4706c0ca4.png","timeStamp":1608430463305}],"result":"SUCCESS","precondition":false,"level":3},{"number":13,"description":"user select 3 on dia","duration":610,"startTime":"2020-12-19T21:14:23.307-05:00[America/Bogota]","screenshots":[{"screenshot":"792663569b2b5dc21e79487f419835e68fbb3a2c4dcb00f2a54828d4706c0ca4.png","timeStamp":1608430463308},{"screenshot":"108e81e7b799b72b020df1e318bbcf4f8847f4384694317a5d21ccc6b5b885ab.png","timeStamp":1608430463917}],"result":"SUCCESS","precondition":false,"level":3},{"number":14,"description":"user select 1980 on año","duration":584,"startTime":"2020-12-19T21:14:23.918-05:00[America/Bogota]","screenshots":[{"screenshot":"108e81e7b799b72b020df1e318bbcf4f8847f4384694317a5d21ccc6b5b885ab.png","timeStamp":1608430463921},{"screenshot":"9d47ad6ac9c0d0582067324a8d2f6044c5507f01d4a2604d26747a44b029de55.png","timeStamp":1608430464501}],"result":"SUCCESS","precondition":false,"level":3},{"number":15,"description":"user clicks on boton next","duration":746,"startTime":"2020-12-19T21:14:24.503-05:00[America/Bogota]","screenshots":[{"screenshot":"9d47ad6ac9c0d0582067324a8d2f6044c5507f01d4a2604d26747a44b029de55.png","timeStamp":1608430464505},{"screenshot":"3421a7ac9633f8c07fdd0dc78ff6056a5f66e9f05cd93d03482ed435a597ba88.png","timeStamp":1608430465248}],"result":"SUCCESS","precondition":false,"level":3}]}]},{"number":16,"description":"Y Adiciono mi ciudad de destino Medellín, Antioquía, Colombia y el codigo postal 050010","duration":5984,"startTime":"2020-12-19T21:14:25.256-05:00[America/Bogota]","screenshots":[{"screenshot":"3421a7ac9633f8c07fdd0dc78ff6056a5f66e9f05cd93d03482ed435a597ba88.png","timeStamp":1608430465257},{"screenshot":"5d89f945cdfec69d6621cab59df70f3ef2a092400e2752ba48239b5d3a5bce22.png","timeStamp":1608430471240}],"result":"SUCCESS","precondition":false,"level":1,"children":[{"number":17,"description":"User ingresar datos","duration":5903,"startTime":"2020-12-19T21:14:25.330-05:00[America/Bogota]","screenshots":[{"screenshot":"9a6c5d0dc2e36fc8f1a5d8915b43a8b6f50c384d3d10f4220d20bad987e92684.png","timeStamp":1608430466003},{"screenshot":"5d89f945cdfec69d6621cab59df70f3ef2a092400e2752ba48239b5d3a5bce22.png","timeStamp":1608430471233}],"result":"SUCCESS","precondition":false,"level":2,"children":[{"number":18,"description":"user enters \u0027Medellín, Antioquía, Colombia\u0027 into campo ciudad","duration":2225,"startTime":"2020-12-19T21:14:26.018-05:00[America/Bogota]","screenshots":[{"screenshot":"9a6c5d0dc2e36fc8f1a5d8915b43a8b6f50c384d3d10f4220d20bad987e92684.png","timeStamp":1608430466020},{"screenshot":"262c26213e3fa3b8f0f28fe53f1b1064f42c6ad9523a3a9881667a417f212ca1.png","timeStamp":1608430468242}],"result":"SUCCESS","precondition":false,"level":3},{"number":19,"description":"user enters \u0027050010\u0027 into campo code","duration":949,"startTime":"2020-12-19T21:14:28.268-05:00[America/Bogota]","screenshots":[{"screenshot":"262c26213e3fa3b8f0f28fe53f1b1064f42c6ad9523a3a9881667a417f212ca1.png","timeStamp":1608430468270},{"screenshot":"c2d1fd6454525f62d54f0368eb1105fcf34f947158b017b77e7a3037388995fc.png","timeStamp":1608430469217}],"result":"SUCCESS","precondition":false,"level":3},{"number":20,"description":"user clicks on boton next step 2","duration":997,"startTime":"2020-12-19T21:14:29.220-05:00[America/Bogota]","screenshots":[{"screenshot":"c2d1fd6454525f62d54f0368eb1105fcf34f947158b017b77e7a3037388995fc.png","timeStamp":1608430469221},{"screenshot":"e65e961bba04ad7c8cee53cf4857eedf08e6276c95c04eb5bcbac1a80911b1ea.png","timeStamp":1608430470217}],"result":"SUCCESS","precondition":false,"level":3},{"number":21,"description":"user clicks on boton next step 3","duration":992,"startTime":"2020-12-19T21:14:30.219-05:00[America/Bogota]","screenshots":[{"screenshot":"e65e961bba04ad7c8cee53cf4857eedf08e6276c95c04eb5bcbac1a80911b1ea.png","timeStamp":1608430470221},{"screenshot":"5d89f945cdfec69d6621cab59df70f3ef2a092400e2752ba48239b5d3a5bce22.png","timeStamp":1608430471211}],"result":"SUCCESS","precondition":false,"level":3}]}]}]}],"userStory":{"id":"prueba-reto-sophos","storyName":"Prueba reto sophos","path":"src/test/resources/features/registroutest.feature","type":"feature"},"featureTag":{"name":"Features/Prueba reto sophos","type":"feature","displayName":"Features/Prueba reto sophos"},"title":": Registro en uiTest","tags":[{"name":"Prueba reto sophos","type":"feature","displayName":"Prueba reto sophos"}],"startTime":"2020-12-19T21:14:02.880-05:00[America/Bogota]","duration":29740,"projectKey":"","isManualTestingUpToDate":false,"dataTable":{"headers":["firstname","lastname","email","month","day","year","city","postalcod"],"rows":[{"values":["jhon","smith","jhon@gmail.com","March","3","1980","Medellín, Antioquía, Colombia","050010"],"result":"SUCCESS"}],"predefinedRows":true,"scenarioOutline":"Dado abro la pagina\n\rCuando me quiero registrar con los datos personales\n\rY Adiciono mi ciudad de destino \u003ccity\u003e y el codigo postal \u003cpostalcod\u003e\n\r","dataSetDescriptors":[{"startRow":0,"rowCount":0,"name":""}]},"manual":false,"testSource":"Cucumber","actors":[{"name":"user","can":["browse the web"]}],"result":"SUCCESS","scenarioOutline":"Dado abro la pagina\r\nCuando me quiero registrar con los datos personales\r\n|firstname | lastname | email | month | day | year|\r\n|\u003cfirstname\u003e | \u003clastname\u003e | \u003cemail\u003e | \u003cmonth\u003e | \u003cday\u003e | \u003cyear\u003e|\r\nY Adiciono mi ciudad de destino \u003ccity\u003e y el codigo postal \u003cpostalcod\u003e"}